cryptographyComplements/__init__.py
cryptographyComplements/cryptosystems.py
cryptographyComplements/mathFunctions.py
cryptographyComplements/primalityTests.py
cryptographyComplements/tools.py
cryptographyComplements-0.3.5.dist-info/LICENSE
cryptographyComplements-0.3.5.dist-info/METADATA
cryptographyComplements-0.3.5.dist-info/WHEEL
cryptographyComplements-0.3.5.dist-info/top_level.txt
cryptographyComplements-0.3.5.dist-info/RECORD
