Metadata-Version: 2.1
Name: cryptographyComplements
Version: 0.3.5
Summary: A Python library, in development, that allows the user to use cryptography, and related, functions.
Author: Forzo
License: GPL-3.0
Project-URL: Source, https://github.com/Forzooo/cryptographyComplements
Project-URL: Documentation, https://cryptographycomplements.readthedocs.io/
Classifier: Programming Language :: Python :: 3
License-File: LICENSE
